COPYING
COPYING.tff
MANIFEST.in
README.rst
requirements.txt
setup.py
test/test.py
trachet/__init__.py
trachet/char.py
trachet/constant.py
trachet/controller.py
trachet/csi.py
trachet/cstr.py
trachet/esc.py
trachet/input.py
trachet/iomode.py
trachet/output.py
trachet/seqdb.py
trachet/ss2.py
trachet/ss3.py
trachet/template.py
trachet/tffstub.py
trachet/trace.py
trachet/trachet.py
trachet.egg-info/PKG-INFO
trachet.egg-info/SOURCES.txt
trachet.egg-info/dependency_links.txt
trachet.egg-info/eager_resources.txt
trachet.egg-info/entry_points.txt
trachet.egg-info/requires.txt
trachet.egg-info/top_level.txt
trachet.egg-info/zip-safe
trachet/tff/__init__.py
trachet/tff/setup.py
trachet/tff/tff.py