Metadata-Version: 1.1
Name: trachet
Version: 1.0.8
Summary: Step-by-step/realtime terminal debugger.  It tell you what is happening on your terminal.
Home-page: http://saitoha.github.com/trachet
Author: Hayaki Saito (user@zuse.jp)
Author-email: user@zuse.jp
License: GPL v3
Keywords: terminal debugger
Platform: UNKNOWN
Classifier: Development Status :: 4 - Beta
Classifier: Topic :: Terminals
Classifier: Environment :: Console
Classifier: Intended Audience :: Developers
Classifier: License :: OSI Approved :: GNU General Public License (GPL)
Classifier: Programming Language :: Python
